ezinfra/__init__.py
ezinfra/cloudinit.py
ezinfra/proxy.py
ezinfra/pve.py
ezinfra/remote.py
ezinfra/repo.py
ezinfra/sshkeys.py
ezinfra/vms.py
ezlab/USAGE.md
ezlab/__init__.py
ezlab/__main__.py
ezlab/app.py
ezlab/ezmeral/ezdf.py
ezlab/ezmeral/ezua.py
ezlab/infra/pve.py
ezlab/main.py
ezlab/pages/df.py
ezlab/pages/ezmeral.py
ezlab/pages/settings.py
ezlab/pages/sshkeys.py
ezlab/pages/targets.py
ezlab/pages/ua.py
ezlab/pages/vms.py
ezlab/parameters.py
ezlab/requirements.txt
ezlab/utils.py
ezlabctl/USAGE.md
ezlabctl/__init__.py
ezlabctl/__main__.py
ezlabctl/common.py
ezlabctl/config.py
ezlabctl/connect.py
ezlabctl/create.py
ezlabctl/delete.py
ezlabctl/ezdf.py
ezlabctl/ezua.py
ezlabctl/ezua_old.py
ezlabctl/main.py
ezlabctl/parameters.py
ezlabctl/pve.py
ezlabctl/requirements.txt
kayalab-0.11.9.dist-info/LICENSE
kayalab-0.11.9.dist-info/METADATA
kayalab-0.11.9.dist-info/WHEEL
kayalab-0.11.9.dist-info/entry_points.txt
kayalab-0.11.9.dist-info/RECORD
